setup.cfg
setup.py
__plugin__/__init__.py
__plugin__/gateway_acl/__init__.py
__plugin__/gateway_acl/database.py
__plugin__/gateway_acl/patch_ally_core.py
__plugin__/gateway_acl/patch_ally_core_http.py
__plugin__/gateway_acl/service.py
acl/__init__.py
acl/api/__init__.py
acl/api/access.py
acl/api/acl.py
acl/api/compensate.py
acl/api/domain_acl.py
acl/api/filter.py
acl/api/gateway_acl.py
acl/api/group.py
acl/core/__init__.py
acl/core/spec.py
acl/core/impl/__init__.py
acl/core/impl/acl.py
acl/core/impl/compensate.py
acl/core/impl/processor/__init__.py
acl/core/impl/processor/assembler/__init__.py
acl/core/impl/processor/assembler/index_access.py
acl/core/impl/processor/assembler/index_filter.py
acl/core/impl/processor/assembler/process_filter.py
acl/core/impl/processor/gateway/__init__.py
acl/core/impl/processor/gateway/acl_permission.py
acl/core/impl/processor/gateway/anonymous_group.py
acl/core/impl/processor/gateway/compensate.py
acl/core/impl/processor/gateway/permission_gateway.py
acl/core/impl/processor/gateway/root_uri.py
acl/impl/__init__.py
acl/impl/access.py
acl/impl/filter.py
acl/impl/gateway_acl.py
acl/impl/group.py
acl/meta/__init__.py
acl/meta/access.py
acl/meta/acl.py
acl/meta/acl_intern.py
acl/meta/compensate.py
acl/meta/filter.py
acl/meta/group.py
acl/meta/metadata_acl.py
gateway_acl.egg-info/PKG-INFO
gateway_acl.egg-info/SOURCES.txt
gateway_acl.egg-info/dependency_links.txt
gateway_acl.egg-info/top_level.txt
gateway_acl.egg-info/zip-safe