Metadata-Version: 1.0
Name: gateway-acl
Version: 1.0
Summary: This plugin provides the service gateways.
Home-page: http://www.sourcefabric.org/en/superdesk/
Author: UNKNOWN
Author-email: UNKNOWN
License: GPL v3
Platform: all
